fngradio/__init__.py
fngradio/app.py
fngradio/decorators.py
fngradio/py.typed
fngradio/tabbed_interface.py
fngradio-0.0.9.dist-info/METADATA
fngradio-0.0.9.dist-info/WHEEL
fngradio-0.0.9.dist-info/top_level.txt
fngradio-0.0.9.dist-info/RECORD
