Metadata-Version: 2.4
Name: fngradio
Version: 0.0.9
Summary: Define Gradio using type hints
Project-URL: homepage, https://github.com/de-code/fngradio
Project-URL: repository, https://github.com/de-code/fngradio
Requires-Python: >=3.10
Requires-Dist: gradio>=5.37.0
Requires-Dist: pydantic>=2.11.7
